dudl/__init__.py
dudl/dudl_app.py
dudl/env.py
dudl/utils.py
dudl/blueprints/__init__.py
dudl/blueprints/dudl_blueprint.py
dudl/blueprints/swag/__init__.py
dudl/models/__init__.py
dudl/models/game.py
dudl/models/gamecollection.py
dudl/models/playerprofile.py
dudl-0.6.0.dist-info/LICENSE
dudl-0.6.0.dist-info/METADATA
dudl-0.6.0.dist-info/WHEEL
dudl-0.6.0.dist-info/entry_points.txt
dudl-0.6.0.dist-info/top_level.txt
dudl-0.6.0.dist-info/RECORD
